MANIFEST.in
README.mkdn
setup.py
Savoir/Savoir.py
Savoir/__init__.py
Savoir.egg-info/PKG-INFO
Savoir.egg-info/SOURCES.txt
Savoir.egg-info/dependency_links.txt
Savoir.egg-info/requires.txt
Savoir.egg-info/top_level.txt