Metadata-Version: 1.0
Name: Savoir
Version: 1.0.5
Summary: A python wrapper for Multichain Json-RPC API 
Home-page: https://github.com/DXMarkets/Savoir
Author: Federico Cardoso
Author-email: federico.cardoso@dxmarkets.com
License: BSD
Keywords: multichain python blockchain jsonrpc
Platform: UNKNOWN
